filename_sanitizer/__init__.py
filename_sanitizer-0.1.0.dist-info/LICENSE
filename_sanitizer-0.1.0.dist-info/METADATA
filename_sanitizer-0.1.0.dist-info/WHEEL
filename_sanitizer-0.1.0.dist-info/top_level.txt
filename_sanitizer-0.1.0.dist-info/RECORD
