Metadata-Version: 2.1
Name: filename-sanitizer
Version: 0.1.0
Summary: A Python 2.7/3.2+ package to sanitize filenames in a (hopefully) cross-platform, cross-filesystem manner.
Home-page: https://github.com/ksze/filename-sanitizer
Author: Kal Sze (twitter.com/k_sze, github.com/ksze)
Author-email: swordangel@gmail.com
License: BSD
Keywords: filename sanitization
Platform: UNKNOWN
Classifier: Development Status :: 4 - Beta
Classifier: Topic :: Utilities
Classifier: License :: OSI Approved :: BSD License
Classifier: Programming Language :: Python :: 2.7
Classifier: Programming Language :: Python :: 3.2
Classifier: Programming Language :: Python :: 3.3
Classifier: Programming Language :: Python :: 3.4
Classifier: Programming Language :: Python :: 3.5
Classifier: Programming Language :: Python :: 3.6
Classifier: Programming Language :: Python :: 3.7
Classifier: Topic :: System :: Filesystems
